es_cleaner/__init__.py
es_metricbeats_cleaner-1.0.dist-info/METADATA
es_metricbeats_cleaner-1.0.dist-info/RECORD
es_metricbeats_cleaner-1.0.dist-info/WHEEL
es_metricbeats_cleaner-1.0.dist-info/entry_points.txt
es_metricbeats_cleaner-1.0.dist-info/top_level.txt
