Metadata-Version: 2.1
Name: es-metricbeats-cleaner
Version: 1.0
Summary: Elasticsearch cleanup for metricbeats
Home-page: UNKNOWN
Author: Omar Diaz
Author-email: diaz@autoaid.de
License: UNKNOWN
Platform: UNKNOWN
Requires-Dist: elasticsearch
